odoo/addons/l10n_mx_res_partner/README.rst
odoo/addons/l10n_mx_res_partner/__init__.py
odoo/addons/l10n_mx_res_partner/__manifest__.py
odoo/addons/l10n_mx_res_partner/i18n/es.po
odoo/addons/l10n_mx_res_partner/i18n/l10n_mx_res_partner.pot
odoo/addons/l10n_mx_res_partner/models/__init__.py
odoo/addons/l10n_mx_res_partner/models/res_partner.py
odoo/addons/l10n_mx_res_partner/readme/CONTRIBUTORS.rst
odoo/addons/l10n_mx_res_partner/readme/CREDITS.rst
odoo/addons/l10n_mx_res_partner/readme/DESCRIPTION.rst
odoo/addons/l10n_mx_res_partner/readme/USAGE.rst
odoo/addons/l10n_mx_res_partner/static/description/icon.png
odoo/addons/l10n_mx_res_partner/static/description/index.html
odoo13_addon_l10n_mx_res_partner-13.0.1.0.1.dev9.dist-info/METADATA
odoo13_addon_l10n_mx_res_partner-13.0.1.0.1.dev9.dist-info/WHEEL
odoo13_addon_l10n_mx_res_partner-13.0.1.0.1.dev9.dist-info/top_level.txt
odoo13_addon_l10n_mx_res_partner-13.0.1.0.1.dev9.dist-info/RECORD
